{"JsDvuk6G6YprJsknJBM+EA==":"logo-real-madrid-dep-nhat-5.jpg","GqXAGqq4z1BoGZYDtLxidw==":"logo-real-madrid-dep-nhat-5.jpeg","umrA7N3jrBsW4h33ZjcK3A==":"image-116.png","XrgSmv11fyiv3oWnZR9BnQ==":"anh-mo-ta.jpg","HeOWfeFMXbbSIBDESgf6HA==":"messi-1.7747386582441461e+22.webp","Kkhy8560vVtvzZJ7SIri8w==":"2024-07-05t210215z828248098up1ek751mfqfvrtrmadp3soccer-euro-por-fra-report-1.webp","BrcYsh9hqgiw5wizLcLxCg==":"0735-mu-vs-liver.jpg","gn+S2UgAVF9gx6dBEItTQQ==":"0735-mu-vs-liver.jpeg","J185JiqGe7NffuwVVE+Aog==":"images145875-liverpool626.jpg","ZT3zFNOyaWQUtsps5cAT2g==":"lich-thi-dau-bong-da-hom-nay-31-3.jpeg","X9QXPiwGdUweR71knla7Ag==":"anh-vs-nhat-ban-nhan-dinh-680.jpg","Voq3rZJvkT9x/sZ9ubQiMA==":"2c5c97cf2b7135df004fe3032aa68d25b451f3dc67d927da3f20a604acc1b09d-800.webp","FCjRbgLZAKyUO9uk3xLBOw==":"lich-thi-dau-world-cup-26-1.webp","Kj4UbBHgCcEzKMjElw+TjQ==":"hinh-nen-san-bong-dep-banner.jpg","IeEcQ1QWxowsw8KohU8FrA==":"cach-chon-bong-da-theo-size-38-820f375df1d04b8f87c4e85b5e6f13d1.jpg","N9nedRa9TZ3/wpOSWcJH2w==":"thumb-660-67b872c1-ab2e-470c-b521-0dbca8992040.jpg","KGifHPKHZchoo9e7E/JFrQ==":"soccer-football-field-illustration-paint-600w-2727189481.webp"}